MANIFEST.in
README.md
db_config.ini
example.py
setup.py
dburi/__init__.py
dburi/config.py
dburi/conts.py
dburi/dburi.py
dburi.egg-info/PKG-INFO
dburi.egg-info/SOURCES.txt
dburi.egg-info/dependency_links.txt
dburi.egg-info/requires.txt
dburi.egg-info/top_level.txt